{"timestamp":"2026-04-14T08:01:00Z","sites":[{"name":"ExtendPad","url":"https://frankfu0714-cyber.github.io/extendpad-privacy/privacy-policy.html","site_status":"UP","http_code":"200"},{"name":"OnePost","url":"https://onepost-lovat.vercel.app","site_status":"UP","http_code":"307"},{"name":"VideoEssay","url":"https://frankfu0714-cyber.github.io/Video-Essay-Simulator/","site_status":"UP","http_code":"200"},{"name":"AudioFixStudio","url":"https://martinfu1997.github.io/audio-fix-studio/","site_status":"UP","http_code":"200"},{"name":"Kanban","url":"https://martinfu1997.github.io/kanban/","site_status":"UP","http_code":"200"}]}
